README.rst
setup.cfg
setup.py
mordred/ABCIndex.py
mordred/AcidBase.py
mordred/AdjacencyMatrix.py
mordred/Aromatic.py
mordred/AtomCount.py
mordred/Autocorrelation.py
mordred/BCUT.py
mordred/BalabanJ.py
mordred/BaryszMatrix.py
mordred/BertzCT.py
mordred/BondCount.py
mordred/CPSA.py
mordred/CarbonTypes.py
mordred/Chi.py
mordred/Constitutional.py
mordred/DetourMatrix.py
mordred/DistanceMatrix.py
mordred/EState.py
mordred/EccentricConnectivityIndex.py
mordred/ExtendedTopochemicalAtom.py
mordred/FragmentComplexity.py
mordred/Framework.py
mordred/GeometricalIndex.py
mordred/GravitationalIndex.py
mordred/HydrogenBond.py
mordred/InformationContent.py
mordred/KappaShapeIndex.py
mordred/Lipinski.py
mordred/LogS.py
mordred/McGowanVolume.py
mordred/MoRSE.py
mordred/MoeType.py
mordred/MolecularDistanceEdge.py
mordred/MolecularId.py
mordred/MomentOfInertia.py
mordred/PathCount.py
mordred/Polarizability.py
mordred/RingCount.py
mordred/RotatableBond.py
mordred/SLogP.py
mordred/TopoPSA.py
mordred/TopologicalCharge.py
mordred/TopologicalIndex.py
mordred/VdwVolumeABC.py
mordred/VertexAdjacencyInformation.py
mordred/WalkCount.py
mordred/Weight.py
mordred/WienerIndex.py
mordred/ZagrebIndex.py
mordred/__init__.py
mordred/__main__.py
mordred/_atomic_property.py
mordred/_graph_matrix.py
mordred/_matrix_attributes.py
mordred/_util.py
mordred/_version.py
mordred/_version.txt
mordred.egg-info/PKG-INFO
mordred.egg-info/SOURCES.txt
mordred.egg-info/dependency_links.txt
mordred.egg-info/requires.txt
mordred.egg-info/top_level.txt
mordred/_base/__init__.py
mordred/_base/calculator.py
mordred/_base/context.py
mordred/_base/descriptor.py
mordred/_base/pandas_module.py
mordred/_base/parallel.py
mordred/_base/result.py
mordred/_base/util.py
mordred/data/allred_rocow_electron_negativity.txt
mordred/data/ionization_potential.txt
mordred/data/mass.txt
mordred/data/mc_gowan_volume.txt
mordred/data/pauling_electron_negativity.txt
mordred/data/polarizalibity78.txt
mordred/data/polarizalibity94.txt
mordred/data/sanderson_electron_negativity.txt
mordred/data/van_der_waals_radii.txt
mordred/descriptors/__init__.py
mordred/error/__init__.py
