Metadata-Version: 1.0
Name: mordred
Version: 1.1.2
Summary: molecular descriptor calculator
Home-page: https://github.com/mordred-descriptor/mordred
Author: Hirotomo Moriwaki
Author-email: philopon.dependence@gmail.com
License: BSD-3-Clause
Keywords: QSAR chemoinformatics
Platform: any
